plone.locking-3.0.2-py3.13-nspkg.pth
plone/locking/__init__.py
plone/locking/configure.zcml
plone/locking/events.py
plone/locking/interfaces.py
plone/locking/lockable.py
plone/locking/testing.py
plone/locking/browser/__init__.py
plone/locking/browser/info.pt
plone/locking/browser/info.py
plone/locking/browser/locking.py
plone/locking/tests/__init__.py
plone/locking/tests/locking.rst
plone/locking/tests/test_functional.py
plone/locking/tests/test_views.py
plone.locking-3.0.2.dist-info/METADATA
plone.locking-3.0.2.dist-info/WHEEL
plone.locking-3.0.2.dist-info/namespace_packages.txt
plone.locking-3.0.2.dist-info/top_level.txt
plone.locking-3.0.2.dist-info/RECORD
